Workbook

Sheet Data
A1: Order ID | B1: Order Date | C1: Ship Date | D1: Customer Name | E1: Segment | F1: Region | G1: State | H1: Category | I1: Sub-Category | J1: Sales | K1: Quantity | L1: Discount | M1: Profit
A2: US-2025-100205 | B2: 45659 | C2: 45661 | D2: Jack Wilson | E2: Corporate | F2: West | G2: Oregon | H2: Office Supplies | I2: Binders | J2: 67.8 | K2: 3 | L2: 0.1 | M2: 20.54
A3: US-2025-100189 | B3: 45660 | C3: 45666 | D3: Frank Ocean | E3: Corporate | F3: West | G3: Oregon | H3: Furniture | I3: Bookcases | J3: 348.24 | K3: 2 | L3: 0.2 | M3: 9.49
A4: US-2025-100195 | B4: 45661 | C4: 45665 | D4: Maya Patel | E4: Consumer | F4: West | G4: Washington | H4: Technology | I4: Accessories | J4: 149.82 | K4: 3 | L4: 0.1 | M4: 34.81
A5: US-2025-100058 | B5: 45664 | C5: 45669 | D5: Priya Nair | E5: Consumer | F5: Central | G5: Illinois | H5: Furniture | I5: Bookcases | J5: 1133.01 | K5: 6 | L5: 0.2 | M5: 19.33
A6: US-2025-100136 | B6: 45667 | C6: 45671 | D6: Jack Wilson | E6: Consumer | F6: Central | G6: Texas | H6: Technology | I6: Phones | J6: 1157.31 | K6: 9 | L6: 0.2 | M6: 176.31
A7: US-2025-100142 | B7: 45671 | C7: 45676 | D7: Barry Weir | E7: Corporate | F7: Central | G7: Michigan | H7: Technology | I7: Accessories | J7: 213.98 | K7: 7 | L7: 0 | M7: 60.27
A8: US-2025-100159 | B8: 45671 | C8: 45678 | D8: Frank Ocean | E8: Corporate | F8: East | G8: Pennsylvania | H8: Furniture | I8: Tables | J8: 1932.15 | K8: 7 | L8: 0 | M8: -164.31
A9: US-2025-100054 | B9: 45673 | C9: 45676 | D9: Grace Kim | E9: Consumer | F9: East | G9: Pennsylvania | H9: Technology | I9: Accessories | J9: 205.67 | K9: 6 | L9: 0 | M9: 57.2
A10: US-2025-100017 | B10: 45674 | C10: 45678 | D10: Carol Nguyen | E10: Home Office | F10: East | G10: New York | H10: Furniture | I10: Chairs | J10: 95.96 | K10: 1 | L10: 0.2 | M10: 10.16
A11: US-2025-100157 | B11: 45675 | C11: 45678 | D11: Carol Nguyen | E11: Consumer | F11: South | G11: North Carolina | H11: Technology | I11: Phones | J11: 861.18 | K11: 3 | L11: 0 | M11: 167.82
A12: US-2025-100037 | B12: 45677 | C12: 45679 | D12: Noah Scott | E12: Corporate | F12: Central | G12: Michigan | H12: Office Supplies | I12: Storage | J12: 42.94 | K12: 1 | L12: 0 | M12: 6.35
A13: US-2025-100121 | B13: 45681 | C13: 45684 | D13: Maya Patel | E13: Home Office | F13: Central | G13: Texas | H13: Office Supplies | I13: Supplies | J13: 35.93 | K13: 2 | L13: 0.2 | M13: 3.21
... A221: US-2025-100081 | B221: 46021 | C221: 46024 | D221: Jack Wilson | E221: Home Office | F221: West | G221: California | H221: Office Supplies | I221: Supplies | J221: 125.6 | K221: 8 | L221: 0.2 | M221: 11.42

Sheet Report
B2: Superstore Sales & Profit Report
B3: Prepared by Yuan Li - S390310 | Report Writer role, Reporting Fundamentals practice task
B5: Q1. What are our total sales by product category?
B6: Stakeholder: Merchandising team - which category should we invest marketing budget in?
B8: Category | C8: Total Sales
B9: Furniture | C9: =SUMIF(Data!$H$2:$H$221,B9,Data!$J$2:$J$221) -> 48273.83
B10: Office Supplies | C10: =SUMIF(Data!$H$2:$H$221,B10,Data!$J$2:$J$221) -> 11855.33
B11: Technology | C11: =SUMIF(Data!$H$2:$H$221,B11,Data!$J$2:$J$221) -> 71222.3
B21: Q2. How do sales and profit compare across regions?
B22: Stakeholder: Regional sales managers - which region is performing best, and where is profit being lost?
B24: Region | C24: Total Sales | D24: Total Profit
B25: East | C25: =SUMIF(Data!$F$2:$F$221,B25,Data!$J$2:$J$221) -> 38588.07 | D25: =SUMIF(Data!$F$2:$F$221,B25,Data!$M$2:$M$221) -> 3270.85
B26: West | C26: =SUMIF(Data!$F$2:$F$221,B26,Data!$J$2:$J$221) -> 28530.71 | D26: =SUMIF(Data!$F$2:$F$221,B26,Data!$M$2:$M$221) -> 1554.51
B27: Central | C27: =SUMIF(Data!$F$2:$F$221,B27,Data!$J$2:$J$221) -> 25943.95 | D27: =SUMIF(Data!$F$2:$F$221,B27,Data!$M$2:$M$221) -> 2681.27
B28: South | C28: =SUMIF(Data!$F$2:$F$221,B28,Data!$J$2:$J$221) -> 38288.73 | D28: =SUMIF(Data!$F$2:$F$221,B28,Data!$M$2:$M$221) -> 3037.84
B38: Q3. What does our monthly sales trend look like over the year?
B39: Stakeholder: Finance team - are sales seasonal, and what should next year's forecast assume?
B41: Month | C41: Total Sales
B42: Jan | C42: =SUMPRODUCT((Data!$B$2:$B$221>=DATE(2025,1,1))*(Data!$B$2:$B$221<DATE(2025,2,1))*Data!$J$2:$J$221) -> 7483.57
B43: Feb | C43: =SUMPRODUCT((Data!$B$2:$B$221>=DATE(2025,2,1))*(Data!$B$2:$B$221<DATE(2025,3,1))*Data!$J$2:$J$221) -> 6383.5
B44: Mar | C44: =SUMPRODUCT((Data!$B$2:$B$221>=DATE(2025,3,1))*(Data!$B$2:$B$221<DATE(2025,4,1))*Data!$J$2:$J$221) -> 14594.92
B45: Apr | C45: =SUMPRODUCT((Data!$B$2:$B$221>=DATE(2025,4,1))*(Data!$B$2:$B$221<DATE(2025,5,1))*Data!$J$2:$J$221) -> 7413.07
B46: May | C46: =SUMPRODUCT((Data!$B$2:$B$221>=DATE(2025,5,1))*(Data!$B$2:$B$221<DATE(2025,6,1))*Data!$J$2:$J$221) -> 20931.36
B47: Jun | C47: =SUMPRODUCT((Data!$B$2:$B$221>=DATE(2025,6,1))*(Data!$B$2:$B$221<DATE(2025,7,1))*Data!$J$2:$J$221) -> 9114.71
B48: Jul | C48: =SUMPRODUCT((Data!$B$2:$B$221>=DATE(2025,7,1))*(Data!$B$2:$B$221<DATE(2025,8,1))*Data!$J$2:$J$221) -> 9643.9
B49: Aug | C49: =SUMPRODUCT((Data!$B$2:$B$221>=DATE(2025,8,1))*(Data!$B$2:$B$221<DATE(2025,9,1))*Data!$J$2:$J$221) -> 16205.98
B50: Sep | C50: =SUMPRODUCT((Data!$B$2:$B$221>=DATE(2025,9,1))*(Data!$B$2:$B$221<DATE(2025,10,1))*Data!$J$2:$J$221) -> 13114.01
B51: Oct | C51: =SUMPRODUCT((Data!$B$2:$B$221>=DATE(2025,10,1))*(Data!$B$2:$B$221<DATE(2025,11,1))*Data!$J$2:$J$221) -> 9317.09
B52: Nov | C52: =SUMPRODUCT((Data!$B$2:$B$221>=DATE(2025,11,1))*(Data!$B$2:$B$221<DATE(2025,12,1))*Data!$J$2:$J$221) -> 7951.18
B53: Dec | C53: =SUMPRODUCT((Data!$B$2:$B$221>=DATE(2025,12,1))*(Data!$B$2:$B$221<DATE(2025,1,1))*Data!$J$2:$J$221) -> 0
B63: Q4. Who are our top 5 customers by total sales?
B64: Stakeholder: Account management - which customers deserve priority relationship attention?
B65: Rank | C65: Customer | D65: Total Sales
B66: 1 | C66: =INDEX($B$202:$B$219,MATCH(D66,$C$202:$C$219,0)) -> Maya Patel | D66: =LARGE($C$202:$C$219,1) -> 12136.86
B67: 2 | C67: =INDEX($B$202:$B$219,MATCH(D67,$C$202:$C$219,0)) -> Ryan Cole | D67: =LARGE($C$202:$C$219,2) -> 12006.52
B68: 3 | C68: =INDEX($B$202:$B$219,MATCH(D68,$C$202:$C$219,0)) -> Olivia James | D68: =LARGE($C$202:$C$219,3) -> 11856.45
B69: 4 | C69: =INDEX($B$202:$B$219,MATCH(D69,$C$202:$C$219,0)) -> Diego Ramirez | D69: =LARGE($C$202:$C$219,4) -> 11018.14
B70: 5 | C70: =INDEX($B$202:$B$219,MATCH(D70,$C$202:$C$219,0)) -> Harold Pham | D70: =LARGE($C$202:$C$219,5) -> 9205.7
B74: Q5. Which sub-categories have the lowest profit margin?
B75: Stakeholder: Product/pricing team - which sub-categories need a pricing or discount-policy review?
B77: Sub-Category | C77: Total Sales | D77: Total Profit | E77: Profit Margin
B78: Bookcases | C78: =SUMIF(Data!$I$2:$I$221,B78,Data!$J$2:$J$221) -> 11909.19 | D78: =SUMIF(Data!$I$2:$I$221,B78,Data!$M$2:$M$221) -> 529.76 | E78: =IFERROR(D78/C78,0) -> 0.044483294
B79: Chairs | C79: =SUMIF(Data!$I$2:$I$221,B79,Data!$J$2:$J$221) -> 8134.01 | D79: =SUMIF(Data!$I$2:$I$221,B79,Data!$M$2:$M$221) -> 1157.4 | E79: =IFERROR(D79/C79,0) -> 0.14229144
B80: Tables | C80: =SUMIF(Data!$I$2:$I$221,B80,Data!$J$2:$J$221) -> 24626.85 | D80: =SUMIF(Data!$I$2:$I$221,B80,Data!$M$2:$M$221) -> -1455.65 | E80: =IFERROR(D80/C80,0) -> -0.05910825
B81: Furnishings | C81: =SUMIF(Data!$I$2:$I$221,B81,Data!$J$2:$J$221) -> 3603.78 | D81: =SUMIF(Data!$I$2:$I$221,B81,Data!$M$2:$M$221) -> 697.14 | E81: =IFERROR(D81/C81,0) -> 0.19344688
B82: Binders | C82: =SUMIF(Data!$I$2:$I$221,B82,Data!$J$2:$J$221) -> 639.73 | D82: =SUMIF(Data!$I$2:$I$221,B82,Data!$M$2:$M$221) -> 187.27 | E82: =IFERROR(D82/C82,0) -> 0.29273287
B83: Paper | C83: =SUMIF(Data!$I$2:$I$221,B83,Data!$J$2:$J$221) -> 1089.01 | D83: =SUMIF(Data!$I$2:$I$221,B83,Data!$M$2:$M$221) -> 370.99 | E83: =IFERROR(D83/C83,0) -> 0.34066721
B84: Storage | C84: =SUMIF(Data!$I$2:$I$221,B84,Data!$J$2:$J$221) -> 7695.06 | D84: =SUMIF(Data!$I$2:$I$221,B84,Data!$M$2:$M$221) -> 1331.18 | E84: =IFERROR(D84/C84,0) -> 0.1729915
B85: Supplies | C85: =SUMIF(Data!$I$2:$I$221,B85,Data!$J$2:$J$221) -> 2431.53 | D85: =SUMIF(Data!$I$2:$I$221,B85,Data!$M$2:$M$221) -> 204.31 | E85: =IFERROR(D85/C85,0) -> 0.084025284
B86: Accessories | C86: =SUMIF(Data!$I$2:$I$221,B86,Data!$J$2:$J$221) -> 5119.99 | D86: =SUMIF(Data!$I$2:$I$221,B86,Data!$M$2:$M$221) -> 1289.86 | E86: =IFERROR(D86/C86,0) -> 0.25192627
B87: Machines | C87: =SUMIF(Data!$I$2:$I$221,B87,Data!$J$2:$J$221) -> 38518.05 | D87: =SUMIF(Data!$I$2:$I$221,B87,Data!$M$2:$M$221) -> 1690.18 | E87: =IFERROR(D87/C87,0) -> 0.043880207
B88: Phones | C88: =SUMIF(Data!$I$2:$I$221,B88,Data!$J$2:$J$221) -> 27584.26 | D88: =SUMIF(Data!$I$2:$I$221,B88,Data!$M$2:$M$221) -> 4542.03 | E88: =IFERROR(D88/C88,0) -> 0.16466021
B90: Note: 'Working data' block under Q4 supports the ranking formulas (LARGE/INDEX/MATCH) and is not a separate question.
B200: Working data: all customers (used by the ranking formulas in Q4 above)
B201: Customer | C201: Total Sales
B202: Aaron Bergman | C202: =SUMIF(Data!$D$2:$D$221,B202,Data!$J$2:$J$221) -> 5179.03
B203: Barry Weir | C203: =SUMIF(Data!$D$2:$D$221,B203,Data!$J$2:$J$221) -> 5579.39
B204: Carol Nguyen | C204: =SUMIF(Data!$D$2:$D$221,B204,Data!$J$2:$J$221) -> 8785.45
B205: Diego Ramirez | C205: =SUMIF(Data!$D$2:$D$221,B205,Data!$J$2:$J$221) -> 11018.14
B206: Ella Fitzgerald | C206: =SUMIF(Data!$D$2:$D$221,B206,Data!$J$2:$J$221) -> 5198.95
B207: Frank Ocean | C207: =SUMIF(Data!$D$2:$D$221,B207,Data!$J$2:$J$221) -> 7433.17
B208: Grace Kim | C208: =SUMIF(Data!$D$2:$D$221,B208,Data!$J$2:$J$221) -> 4351.39
B209: Harold Pham | C209: =SUMIF(Data!$D$2:$D$221,B209,Data!$J$2:$J$221) -> 9205.7
B210: Ivy Chen | C210: =SUMIF(Data!$D$2:$D$221,B210,Data!$J$2:$J$221) -> 7387.47
B211: Jack Wilson | C211: =SUMIF(Data!$D$2:$D$221,B211,Data!$J$2:$J$221) -> 5770.8
B212: Karen Blake | C212: =SUMIF(Data!$D$2:$D$221,B212,Data!$J$2:$J$221) -> 6009.18
B213: Liam Turner | C213: =SUMIF(Data!$D$2:$D$221,B213,Data!$J$2:$J$221) -> 2071.88
... B219: Ryan Cole | C219: =SUMIF(Data!$D$2:$D$221,B219,Data!$J$2:$J$221) -> 12006.52
